Sure, looking at `SealedJava`:
```scala
// class version 50.0 (50)
// access flags 0x421
public abstract class mjburghoffer/ParentSealedJava {

  // access flags 0x1008
  static synthetic INNERCLASS mjburghoffer/ParentSealedJava$1 null null
  // access flags 0x19
  public final static INNERCLASS mjburghoffer/ParentSealedJava$ChildSealedJava mjburghoffer/ParentSealedJava ChildSealedJava

  // access flags 0x2
  private <init>()V
   L0
    LINENUMBER 5 L0
    ALOAD 0
    INVOKESPECIAL java/lang/Object.<init> ()V
    RETURN
   L1
    LOCALVARIABLE this Lmjburghoffer/ParentSealedJava; L0 L1 0
    MAXSTACK = 1
    MAXLOCALS = 1

  // access flags 0x1000
  synthetic <init>(Lmjburghoffer/ParentSealedJava$1;)V
   L0
    LINENUMBER 3 L0
    ALOAD 0
    INVOKESPECIAL mjburghoffer/ParentSealedJava.<init> ()V
    RETURN
   L1
    LOCALVARIABLE this Lmjburghoffer/ParentSealedJava; L0 L1 0
    LOCALVARIABLE x0 Lmjburghoffer/ParentSealedJava$1; L0 L1 1
    MAXSTACK = 1
    MAXLOCALS = 2
}


// class version 50.0 (50)
// access flags 0x31
public final class mjburghoffer/ParentSealedJava$ChildSealedJava extends mjburghoffer/ParentSealedJava  {

  // access flags 0x19
  public final static INNERCLASS mjburghoffer/ParentSealedJava$ChildSealedJava mjburghoffer/ParentSealedJava ChildSealedJava
  // access flags 0x1008
  static synthetic INNERCLASS mjburghoffer/ParentSealedJava$1 null null

  // access flags 0x1
  public <init>()V
   L0
    LINENUMBER 7 L0
    ALOAD 0
    ACONST_NULL
    INVOKESPECIAL mjburghoffer/ParentSealedJava.<init> (Lmjburghoffer/ParentSealedJava$1;)V
    RETURN
   L1
    LOCALVARIABLE this Lmjburghoffer/ParentSealedJava$ChildSealedJava; L0 L1 0
    MAXSTACK = 2
    MAXLOCALS = 1
}
```


Looking at `SealedKotlin`:
```scala
// class version 50.0 (50)
// access flags 0x421
public abstract class mjburghoffer/ParentSealedKotlin {

  // access flags 0x2
  private <init>()V
   L0
    LINENUMBER 3 L0
    ALOAD 0
    INVOKESPECIAL java/lang/Object.<init> ()V
    RETURN
   L1
    LOCALVARIABLE this Lmjburghoffer/ParentSealedKotlin; L0 L1 0
    MAXSTACK = 1
    MAXLOCALS = 1

  // access flags 0x1001
  public synthetic <init>(Lkotlin/jvm/internal/DefaultConstructorMarker;)V
   L0
    LINENUMBER 3 L0
    ALOAD 0
    INVOKESPECIAL mjburghoffer/ParentSealedKotlin.<init> ()V
    RETURN
   L1
    LOCALVARIABLE this Lmjburghoffer/ParentSealedKotlin; L0 L1 0
    LOCALVARIABLE $constructor_marker Lkotlin/jvm/internal/DefaultConstructorMarker; L0 L1 1
    MAXSTACK = 1
    MAXLOCALS = 2

  @Lkotlin/Metadata;(mv={1, 1, 1}, bv={1, 0, 0}, k=1, d1={"\u0000\u000c\n\u0002\u0018\u0002\n\u0002\u0010\u0000\n\u0002\u0008\u0003\u00086\u0018\u00002\u00020\u0001:\u0001\u0003B\u0007\u0008\u0002\u00a2\u0006\u0002\u0010\u0002\u00a8\u0006\u0004"}, d2={"Lmjburghoffer/ParentSealedKotlin;", "", "()V", "ChildSealedKotlin", "production sources for module scala-kotlin-innerclass-bug-kotlin"})
  // access flags 0x19
  public final static INNERCLASS mjburghoffer/ParentSealedKotlin$ChildSealedKotlin mjburghoffer/ParentSealedKotlin ChildSealedKotlin
}


// class version 50.0 (50)
// access flags 0x31
public final class mjburghoffer/ParentSealedKotlin$ChildSealedKotlin extends mjburghoffer/ParentSealedKotlin  {

  // access flags 0x1
  public <init>()V
   L0
    LINENUMBER 4 L0
    ALOAD 0
    ACONST_NULL
    INVOKESPECIAL mjburghoffer/ParentSealedKotlin.<init> (Lkotlin/jvm/internal/DefaultConstructorMarker;)V
    RETURN
   L1
    LOCALVARIABLE this Lmjburghoffer/ParentSealedKotlin$ChildSealedKotlin; L0 L1 0
    MAXSTACK = 2
    MAXLOCALS = 1

  @Lkotlin/Metadata;(mv={1, 1, 1}, bv={1, 0, 0}, k=1, d1={"\u0000\u000c\n\u0002\u0018\u0002\n\u0002\u0018\u0002\n\u0002\u0008\u0002\u0018\u00002\u00020\u0001B\u0005\u00a2\u0006\u0002\u0010\u0002\u00a8\u0006\u0003"}, d2={"Lmjburghoffer/ParentSealedKotlin$ChildSealedKotlin;", "Lmjburghoffer/ParentSealedKotlin;", "()V", "production sources for module scala-kotlin-innerclass-bug-kotlin"})
  // access flags 0x19
  public final static INNERCLASS mjburghoffer/ParentSealedKotlin$ChildSealedKotlin mjburghoffer/ParentSealedKotlin ChildSealedKotlin
}
```

The big difference is presence of of the following in java (that does not exist in kotlin)
```scala
  // access flags 0x1008
  static synthetic INNERCLASS mjburghoffer/ParentSealedJava$1 null null
```
