Sclala:
```scala
def g = {
    val x = synchronized { 1 }
    x
}
```

compiles to:
```scala
public int g();
  Signature: ()I
  Code:
   0:   aload_0
   1:   dup
   2:   astore_2
   3:   monitorenter
   4:   iconst_1
   5:   invokestatic    SI-18; //Method scala/runtime/BoxesUtility.boxToInteger:(I)Ljava/lang/Integer;
   8:   aload_2
   9:   monitorexit
   10:  invokestatic    SI-22; //Method scala/runtime/BoxesUtility.unboxToInt:(Ljava/lang/Object;)I
   13:  istore_1
   14:  iload_1
   15:  ireturn
   16:  aload_2
   17:  monitorexit
   18:  athrow
  Exception table:
   from   to  target type
     4    10    16   any
```

boxToInteger and unboxToInt should be avoided.
