In the Java code below
```
class ImageView { 
    void setTag(Object o) {} 
} 
class Test1 { 
    void foo() { 
        ImageView imageView = null; 
        imageView.setTag(null); 
    } 
} 
```
method `foo` is translated into the following bytecode
```
void foo();
  Code:
   Stack=2, Locals=2, Args_size=1
   0:	aconst_null
   1:	astore_1
   2:	aload_1
   3:	aconst_null
   4:	invokevirtual	#2; //Method ImageView.setTag:(Ljava/lang/Object;)V
   7:	return
```
while in Scala
```
class ImageView {
  def setTag(o: AnyRef) {}
}
class Test {
  def foo {
    var imageView: ImageView = null
    imageView setTag null
  }
}
```
the generated code (2.9.x and trunk) for method `foo` looks as follows:
```
public void foo();
  Code:
   Stack=2, Locals=2, Args_size=1
   0:	aconst_null
   1:	pop
   2:	aconst_null
   3:	astore_1
   4:	aload_1
   5:	aconst_null
   6:	pop
   7:	aconst_null
   8:	invokevirtual	#12; //Method ImageView.setTag:(Ljava/lang/Object;)V
   11:	return
```
Instructions on lines 0,1,5,6 are superfluous.
