The following code results in a VerifyError:

{code}
object Bug {
  class C(pf: PartialFunction[Any, Any])
  case class D() extends C({ case e => e })
  def main(args: Array[String]) {
    D() // VerifyError
  }
}
{code}

Here is the exception trace:

{code}
java.lang.VerifyError: (class: Bug$D, method: <init> signature: ()V) Expecting to find object/array on stack
	at Bug$.main(Bug.scala:5)
	at Bug.main(Bug.scala)
{code}

The cause of the bug is that {{D}}'s {{<init>}} passes {{this}} to the constructor of the anonymous subclass of {{PartialFunction}} before the {{<init>}} method of the superclass {{C}} is invoked.

Here is the bytecode for {{D()}}:

{code}
public Bug$D();
  Code:
   Stack=4, Locals=1, Args_size=1
   0:	aload_0
   1:	new	#72; //class Bug$D$$anonfun$$init$$1
   4:	dup
   5:	aload_0
   6:	invokespecial	#75; //Method Bug$D$$anonfun$$init$$1."<init>":(LBug$D;)V
   9:	invokespecial	#78; //Method Bug$C."<init>":(Lscala/PartialFunction;)V
   12:	aload_0
   13:	invokestatic	#84; //Method scala/Product$class.$init$:(Lscala/Product;)V
   16:	return
{code}

The VerifyError occurs at the {{invokespecial}} at instruction 6, caused by the {{aload_0}} at instruction 5.

Note that the PartialFunction does not refer to {{this}}, so passing it in is unnecessary.
