I'm pleased to see the inclusion of the @static annotation in Scala 2.10.0-M6. I noticed that @static vals don't get marked final, which limits HotSpot optimizations and jeopardizes the fabric of the cosmos. Heads up!
```scala
object Constants {
  import scala.annotation.static
  @static val Const: Int = 0 // should generate a static final field
  @static final val FinalConst: Int = 0 // ditto
}
```
```scala
public class Constants {
  public static int Const;

  public static int FinalConst;

  public static {};
    Code:
       0: iconst_0      
       1: putstatic     #11                 // Field Const:I
       4: iconst_0      
       5: putstatic     #14                 // Field FinalConst:I
       8: return        

  public Constants();
    Code:
       0: aload_0       
       1: invokespecial #17                 // Method java/lang/Object."<init>":()V
       4: return        
}
```
