I have been looking into this further.

Simplifying to only specialize on Int, this code does not generate a blah method that is to int, only to java.lang.Object.

And as I said above, if the variable to act on is in the method definition, we see the same thing.
```scala
class Blah[@specialized (Int) T](a:T) {
  def blah[@specialized (Int) W](f:T=>W):W  = f(a) 
}
```
```scala
public java.lang.Object blah(scala.Function1, scala.reflect.Manifest);
  Code:
   Stack=3, Locals=3, Args_size=3
   0:	aload_0
   1:	aload_1
   2:	aload_2
   3:	invokevirtual	#17; //Method blah$mcI$sp:(Lscala/Function1;Lscala/reflect/Manifest;)Ljava/lang/Object;
   6:	areturn
  LineNumberTable: 
   line 65: 0

  LocalVariableTable: 
   Start  Length  Slot  Name   Signature
   0      7      0    this       Lmarc/junk/Blah$mcI$sp;
   0      7      1    f       Lscala/Function1;
   0      7      2    evidence$16       Lscala/reflect/Manifest;

  Signature: length = 0x2
   00 18 

public java.lang.Object blah$mcI$sp(scala.Function1, scala.reflect.Manifest);
  Code:
   Stack=2, Locals=3, Args_size=3
   0:	aload_1
   1:	aload_0
   2:	getfield	#26; //Field a$mcI$sp:I
   5:	invokestatic	#32; //Method scala/runtime/BoxesRunTime.boxToInteger:(I)Ljava/lang/Integer;
   8:	invokeinterface	#38,  2; //InterfaceMethod scala/Function1.apply:(Ljava/lang/Object;)Ljava/lang/Object;
   13:	areturn
  LineNumberTable: 
   line 66: 0

  LocalVariableTable: 
   Start  Length  Slot  Name   Signature
   0      14      0    this       Lmarc/junk/Blah$mcI$sp;
   0      14      1    f       Lscala/Function1;
   0      14      2    evidence$16       Lscala/reflect/Manifest;

  Signature: length = 0x2
   00 18 

public marc.junk.Blah$mcI$sp(int, scala.reflect.Manifest);
  Code:
   Stack=3, Locals=3, Args_size=3
   0:	aload_0
   1:	iload_1
   2:	putfield	#26; //Field a$mcI$sp:I
   5:	aload_0
   6:	aload_2
   7:	putfield	#42; //Field evidence$15:Lscala/reflect/Manifest;
   10:	aload_0
   11:	iload_1
   12:	invokestatic	#32; //Method scala/runtime/BoxesRunTime.boxToInteger:(I)Ljava/lang/Integer;
   15:	aload_2
   16:	invokespecial	#47; //Method marc/junk/Blah."<init>":(Ljava/lang/Object;Lscala/reflect/Manifest;)V
   19:	return
```
