{code}
public class B$M extends java.lang.Object implements scala.ScalaObject{
public final B $outer;

public java.lang.String z();
  Code:
   0:	new	#9; //class scala/collection/mutable/StringBuilder
   3:	dup
   4:	invokespecial	#13; //Method scala/collection/mutable/StringBuilder."<init>":()V
   7:	ldc	#16; //String child
   9:	invokevirtual	#20; //Method scala/collection/mutable/StringBuilder.append:(Ljava/lang/Object;)Lscala/collection/mutable/StringBuilder;
   12:	aload_0
   13:	invokespecial	#25; //Method A.a:()Ljava/lang/String;
   16:	invokevirtual	#20; //Method scala/collection/mutable/StringBuilder.append:(Ljava/lang/Object;)Lscala/collection/mutable/StringBuilder;
   19:	invokevirtual	#28; //Method scala/collection/mutable/StringBuilder.toString:()Ljava/lang/String;
   22:	areturn

public B B$M$$$outer();
  Code:
   0:	aload_0
   1:	getfield	#34; //Field $outer:LB;
   4:	areturn

public B$M(B);
  Code:
   0:	aload_1
   1:	ifnonnull	12
   4:	new	#37; //class java/lang/NullPointerException
   7:	dup
   8:	invokespecial	#38; //Method java/lang/NullPointerException."<init>":()V
   11:	athrow
   12:	aload_0
   13:	aload_1
   14:	putfield	#34; //Field $outer:LB;
   17:	aload_0
   18:	invokespecial	#41; //Method java/lang/Object."<init>":()V
   21:	return

}
{code}
