
{code}
scala> class C { new Wrapper(new Array[Int](0)) }
defined class C

scala> :javap -v C
...
{
public C();
  Code:
   Stack=2, Locals=1, Args_size=1
   0:	aload_0
   1:	invokespecial	#9; //Method java/lang/Object."<init>":()V
   4:	getstatic	#15; //Field scala/runtime/ScalaRunTime$.MODULE$:Lscala/runtime/ScalaRunTime$;
   7:	iconst_0
   8:	newarray int
   10:	invokevirtual	#19; //Method scala/runtime/ScalaRunTime$.toObjectArray:(Ljava/lang/Object;)[Ljava/lang/Object;
   13:	checkcast	#21; //class "[Ljava/lang/Integer;"
   16:	pop
   17:	return
  LocalVariableTable:
   Start  Length  Slot  Name   Signature
   0      18      0    this       LC;

  LineNumberTable:
   line 8: 0


}
{code}
