This issue is present on both trunk and 2.7.x.

j/J.java:
{code}
package j;

public class J {
  protected void foo() {
    System.out.println("J.foo()");
  }
}
{code}

s/S.scala:
{code}
package s

import j.J

trait S extends J {
  def bar() {
    foo()
  }
}

class SC extends J with S

object Test {
  def main(args : Array[String]) {
    (new SC).bar()
  }
}
{code}

These compile without error (either compiling the Java first then the Scala; or compiling both the Scala and Java with scalac first, then the Java with javac). On running the following stacktrace is generated,

{code}
java.lang.IllegalAccessError: tried to access method j.J.foo()V from class s.S$$class
	at s.S$$class.bar(S.scala:7)
	at s.SC.bar(S.scala:11)
	at s.Test$$.main(S.scala:15)
	at s.Test.main(S.scala)
	at sun.reflect.NativeMethodAccessorImpl.invoke0(Native Method)
	at sun.reflect.NativeMethodAccessorImpl.invoke(NativeMethodAccessorImpl.java:39)
	at sun.reflect.DelegatingMethodAccessorImpl.invoke(DelegatingMethodAccessorImpl.java:25)
	at java.lang.reflect.Method.invoke(Method.java:597)
	at scala.util.ScalaClassLoader$$$$anonfun$$run$$1.apply(ClassLoader.scala:54)
	at scala.util.ScalaClassLoader$$class.asContext(ClassLoader.scala:21)
	at scala.util.URLClassLoader.asContext(ClassLoader.scala:58)
	at scala.util.ScalaClassLoader$$class.run(ClassLoader.scala:54)
	at scala.util.URLClassLoader.run(ClassLoader.scala:58)
	at scala.tools.nsc.ObjectRunner$$.run(ObjectRunner.scala:33)
	at scala.tools.nsc.MainGenericRunner$$.main(MainGenericRunner.scala:138)
	at scala.tools.nsc.MainGenericRunner.main(MainGenericRunner.scala)
{code}

Viewing the bytecode for s.S$$class shows why this is the case:

{code}
public abstract class s.S$$class extends java.lang.Object{
public static void $$init$$(s.S);
  Code:
   0:	return

public static void bar(s.S);
  Code:
   0:	aload_0
   1:	checkcast	SI-12; //class j/J
   4:	invokevirtual	SI-16; //Method j/J.foo:()V
   7:	return
}
{code}

J.foo is invoked from s.S$$class which does not extend j.J despite trait s.S extending j.J.

It would be great if this could be fixed, but presumably that would involve a significant change to the encoding of traits, so I'd settle for a compile time error for this case.
I just ran into this bug too, working with classloaders.  Interestingly it does not manifest if you explicitly qualify with super.  Change trait S to this:
{code}
  def bar() {
    super.foo()
  }
{code}
and scala s.Test says "J.foo()".  The bytecode looks like this, as a result of the mangling in SuperAccessors.  Perhaps this is as simple as identifying this situation during that phase and treating it like a super invocation?
{code}
public static void bar(s.S);
  Code:
   0:	aload_0
   1:	invokeinterface	SI-16,  1; //InterfaceMethod s/S.s$$S$$$$super$$foo:()V
   6:	return
{code}
Just ran into this with 2.8.1 trying to access a protected field in a mix-in trait. I didn't notice any warnings from the compiler. I got the run-time IllegalAccessError symptom. It happens for me regardless of if I access the protected field via this, naked or through self:

{code}
trait SessionStore {
  self : GenericAutowireComposer =>

  // also tried this.session and session
  def getUser: Option[User] = Option(self.session.getAttribute("user").asInstanceOf[User]

}

class FooCtrl extends GenericAutowireComposer with SessionStore { ... }
{code}


At run-time, I get an IllegalArgumentException:


{code}
java.lang.IllegalAccessError: tried to access field org.zkoss.zk.ui.util.GenericAutowireComposer.session from class FooCtrl$$class
  at FooCtrl$$class.setUser
{code}


I can see that 'fixing' this so that it actually works could be a royal pain. However, generating bytecode that attempts to access protected fields in other classes can't be a Good Thing. Shouldn't this kind of access violation be caught by something in the compiler guts? 
I think I have seen it again, but I failed to minimize it to a sensible code snippet. The general picture of my bug was:
bug/A.java
{code}
package bug;
class A {
  public void addAction(bug.action.Action a) {
     ...
  }
}
{code}

bug/Display.java
{code}
package bug;
class Display {
  protected A sth;
}
{code}

bug/action/Action.java
{code}
package bug.action;
public abstract class Action {
  protected A sth;
  public abstract void run();
}
{code}

and scala code
test/MyDisplay.scala
{code}
package test;

abstract class MyDisplay extends bug.Display {
  def init() {
    sth.addAction(ScalaAction)
  }

  object ScalaAction extends action.Action {
    def run() {
      sth. // call some method on A, crashes on runtime with illegal access
    }
  }
  
}
{code}

The surprising thing is that, if I make ScalaAction a class (and change addAction(...) to addAction(new ScalaAction())) this thing works again.
As I said, I have it reproducible but on a pretty large java and scala library. I will try to dig it more when I find some time.

Got it (I think this is the same bug but maybe I am wrong):
bug/Global.java
{code}
package bug;

import bug.action.Action;
import java.util.List;
import java.util.LinkedList;

public class Global {
  public int items() {
    return 0;
  }

  public int items(int i) {
    return i + ls.size();
  }

  private List<Action> ls = new LinkedList<Action>();

  public void putAction(Action a) {
    a.setGlobal(this);
    ls.add(a);
  }

  public void runActions() {
    for (Action action:  ls) {
      System.out.println("RUNNING ACTION");
      action.run(0);
    }
  }
}
{code}

bug/Display.java
{code}
package bug;

public class Display {
  protected Global m_glob;

  public void start() {
    m_glob.runActions();
  }
}
{code}

bug/action/Action.java
{code}
package bug.action;

import bug.Global;

public abstract class Action {
  protected Global m_glob;

  public Action(Global glob0) {
    m_glob = glob0;
  }
  
  public Action() {
    this(null);
  }

  public abstract void run(int v);

  public void setGlobal(Global g) {
    m_glob = g;
  }
}
{code}

test/ScalaActivity.scala
{code}
package test

import bug.Display
import bug.action.Action

abstract class Outer extends Display {

  def init() {
    m_glob.putAction(ScalaActivity)
  }

  object ScalaActivity extends Action {
    def run(v: Int) {
      val testSet = List(1,2,3)
      testSet.map(p => m_glob.items(p)) // crash with illegal access
    }
  }
}
{code}

test/Test.scala
{code}
package test

import bug.Global

object Test {
  def main(args: Array[String]) {
    val m = new Main()
    m.init()
    m.start()
  }
}

class Main extends Outer {
  m_glob = new Global()
}
{code}

Making ScalaAction a class instead of an object fixed the problem. Closure in run method is necessary to trigger the illegal access error.
Paul, found a counterexample for you: SI-6245.
