When having a singleton object extending another abstract class or trait, we see some problems with Java interoperability. Consider these two base classes:
```scala
abstract class AbstractResult

abstract class Base {
  def call(s: String): AbstractResult
  def callNoArgs: AbstractResult
}
```

We then extend both like this: 
```scala
class ConcreteResult extends AbstractResult

object TwoMethodsSingleton extends Base {
  override def call(s: String) : ConcreteResult = new ConcreteResult
  override def callNoArgs : ConcreteResult = new ConcreteResult
}
```

Note that we override the return type of the methods with a more specific type, ConcreteResult. Calling this code from Scala works as expected.

However, when calling from Java using the generated static forwarders (defined in TwoMethodsSingleton.class), the compiler cannot resolve the method call for the call(s: String) method:

```scala
// Call using static forwarders.
TwoMethodsSingleton.callNoArgs();      // Fine
TwoMethodsSingleton.call("");          // Error: "The method call(String) is ambiguous for the type TwoMethodsSingleton"

// Call directly on the singleton instance.
TwoMethodsSingleton$$.MODULE$$.call(""); // Fine
```

The class file for TwoMethodsSingleton looks like this: 
```scala
// Compiled from TwoMethods.scala (version 1.5 : 49.0, super bit)
public final class org.example.stuff.TwoMethodsSingleton {
  
  // Method descriptor SI-4 ()Lorg/example/stuff/ConcreteResult;
  // Stack: 1, Locals: 0
  public static final org.example.stuff.ConcreteResult callNoArgs();
    0  getstatic org.example.stuff.TwoMethodsSingleton$$.MODULE$$ : org.example.stuff.TwoMethodsSingleton. r11
    3  invokevirtual org.example.stuff.TwoMethodsSingleton$$.callNoArgs() : org.example.stuff.ConcreteResult r13
    6  areturn

  // Method descriptor SI-15 (Ljava/lang/String;)Lorg/example/stuff/ConcreteResult;
  // Stack: 2, Locals: 1
  public static final org.example.stuff.ConcreteResult call(java.lang.String arg0);
    0  getstatic org.example.stuff.TwoMethodsSingleton$$.MODULE$$ : org.example.stuff.TwoMethodsSingleton. r11
    3  aload_0 [arg0]
    4  invokevirtual org.example.stuff.TwoMethodsSingleton$$.call(java.lang.String) : org.example.stuff.ConcreteResult r17
    7  areturn

  // Method descriptor SI-18 ()Lorg/example/stuff/AbstractResult;
  // Stack: 1, Locals: 0
  public static final org.example.stuff.AbstractResult callNoArgs();
    0  getstatic org.example.stuff.TwoMethodsSingleton$$.MODULE$$ : org.example.stuff.TwoMethodsSingleton. r11
    3  invokevirtual org.example.stuff.TwoMethodsSingleton$$.callNoArgs() : org.example.stuff.AbstractResult r20
    6  areturn

  // Method descriptor SI-21 (Ljava/lang/String;)Lorg/example/stuff/AbstractResult;
  // Stack: 2, Locals: 1
  public static final org.example.stuff.AbstractResult call(java.lang.String arg0);
    0  getstatic org.example.stuff.TwoMethodsSingleton$$.MODULE$$ : org.example.stuff.TwoMethodsSingleton. r11
    3  aload_0 [arg0]
    4  invokevirtual org.example.stuff.TwoMethodsSingleton$$.call(java.lang.String) : org.example.stuff.AbstractResult r23
    7  areturn
}
```

I guess it's reasonable that the Java compiler doesn't know which call() method to call here (in the TwoMethodsSingleton$$.class file the "abstract" call() method is marked synthetic bridge). But why does it generate two static forwarders for each method? It doesn't seem like that makes any sense - we're talking static methods anyway.

Why the Java compiler accepts the callNoArgs() method is also strange. It seems to accept methods with primitive types like int for instance, but not real objects.
