I've compiled two files in scala.math (ScalaNumericConversions.scala and ScalaNumber.java) for .NET, hitting a bytecode verification error. The description can be formulated in JVM terms as follows: 

The invocation to ScalaNumber.isWhole() shown below reports a "Method is not visible" error. 

```scala
// Compiled from "ScalaNumericConversions.scala"
public abstract class scala.math.ScalaNumericConversions$$class 
  extends java.lang.Object /*- Note: does not implement scala.Math.ScalaNumber */  {
 . . . 
public static boolean isValidByte(scala.math.ScalaNumericConversions);
  Code:
   0:	aload_0
   1:	checkcast	SI-51; //class scala/math/ScalaNumber 
        /*- But, 
            public abstract class scala.math.ScalaNumber extends java.lang.Number
            so no subclass of this class (scala.math.ScalaNumericConversions$$class)  
            will have scala.Math.ScalaNumber as a base class. 
            The cast will fail. */
   4:	invokevirtual	SI-55; //Method scala/math/ScalaNumber.isWhole:()Z
   7:	ifeq	29
   10:	aload_0
   11:	invokeinterface	SI-59,  1; //InterfaceMethod scala/math/ScalaNumericConversions.toByte:()B
   16:	aload_0
   17:	invokeinterface	SI-61,  1; //InterfaceMethod scala/math/ScalaNumericConversions.toInt:()I
   22:	if_icmpne	29
   25:	iconst_1
   26:	goto	30
   29:	iconst_0
   30:	ireturn
```

Strangely,  scala.math.ScalaNumericConversions$$class does not show up in scala-library.jar

Replying to [comment:1 rytz]:


Oh yes. With that, I could find the real cause (applies to a .NET version). When compiling scala.math.ScalaNumber (a .java file) with ikvmc, 

```scala
public abstract class ScalaNumber extends java.lang.Number {
  protected abstract boolean isWhole();
  public abstract Object underlying();
}
```

the "protected" for isWhole() resulted in famorassem in the .NET counterpart, which for now was being kept in a different assembly from scala-lib (shouldn't). 

Four peverify errors less. 
