I suspect this is actually a bug in the eclipse compiler rather than scala, because the behaviour seems very similar to [https://lampsvn.epfl.ch/trac/scala/ticket/1879 issue 1879] , but don't understand the javap output well enough to be confident of this. Apologies if this is the wrong place; if it is an eclipse compiler problem, assistance in describing the fundamental issue would be greatly appreciated.

The attached is the smallest test case I could manage: there are two subprojects, "server" (java) and "client" (scala). Server contains an interface which uses an annotation. The annotation is an inner class of its own value enum. Client attempts to call a method on the interface.

If I build from the commandline with maven (maven install), it compiles as expected. If I build in eclipse (maven eclipse:eclipse and import the directory), I receive: "error while loading Interface, Missing dependency 'class com.foocorp.AnnotationValue$$Annotation', required by /home/michaeld/tmp/foosys/server/target/classes/com/foocorp/Interface.class". If I then remove the client-> server dependency, and make the client project depend not on the server project in eclipse but on the foosys-server.jar compiled using maven, it compiles without errors. It appears to be the AnnotationValue.class which is relevant, in that replacing that with one or the other version causes the build to fail or succeed.






javap -private -verbose output for commandline-compiled version:

{code}
Compiled from "AnnotationValue.java"       
public final class com.foocorp.AnnotationValue extends java.lang.Enum
  Signature: length = 0x2                                            
   00 21                                                             
  SourceFile: "AnnotationValue.java"                                 
  InnerClass:                                                        
   public abstract SI-12= SI-11 of SI-4; //Annotation=class com/foocorp/AnnotationValue$$Annotation of class com/foocorp/AnnotationValue
  minor version: 0                                                                                                               
  major version: 49                                                                                                              
  Constant pool:                                                                                                                 
const SI-1 = Field        SI-4.SI-36; //  com/foocorp/AnnotationValue.$$VALUES:[Lcom/foocorp/AnnotationValue;                           
const SI-2 = Method       SI-37.SI-38;        //  "[Lcom/foocorp/AnnotationValue;".clone:()Ljava/lang/Object;                          
const SI-3 = class        SI-17;    //  "[Lcom/foocorp/AnnotationValue;"                                                             
const SI-4 = class        SI-39;    //  com/foocorp/AnnotationValue                                                                  
const SI-5 = Method       SI-10.SI-40;        //  java/lang/Enum.valueOf:(Ljava/lang/Class;Ljava/lang/String;)Ljava/lang/Enum;         
const SI-6 = Method       SI-10.SI-41;        //  java/lang/Enum."<init>":(Ljava/lang/String;I)V                                       
const SI-7 = String       SI-14;    //  MEMBER                                                                                       
const SI-8 = Method       SI-4.SI-42; //  com/foocorp/AnnotationValue."<init>":(Ljava/lang/String;I)V                                  
const SI-9 = Field        SI-4.SI-43; //  com/foocorp/AnnotationValue.MEMBER:Lcom/foocorp/AnnotationValue;                             
const SI-10 = class       SI-44;    //  java/lang/Enum                                                                               
const SI-11 = class       SI-45;    //  com/foocorp/AnnotationValue$$Annotation                                                       
const SI-12 = Asciz       Annotation;                                                                                              
const SI-13 = Asciz       InnerClasses;                                                                                            
const SI-14 = Asciz       MEMBER;                                                                                                  
const SI-15 = Asciz       Lcom/foocorp/AnnotationValue;;                                                                           
const SI-16 = Asciz       $$VALUES;                                                                                                 
const SI-17 = Asciz       [Lcom/foocorp/AnnotationValue;;                                                                          
const SI-18 = Asciz       values;                                                                                                  
const SI-19 = Asciz       ()[Lcom/foocorp/AnnotationValue;;                                                                        
const SI-20 = Asciz       Code;                                                                                                    
const SI-21 = Asciz       LineNumberTable;                                                                                         
const SI-22 = Asciz       valueOf;                                                                                                 
const SI-23 = Asciz       (Ljava/lang/String;)Lcom/foocorp/AnnotationValue;;                                                       
const SI-24 = Asciz       LocalVariableTable;                                                                                      
const SI-25 = Asciz       name;                                                                                                    
const SI-26 = Asciz       Ljava/lang/String;;                                                                                      
const SI-27 = Asciz       <init>;                                                                                                  
const SI-28 = Asciz       (Ljava/lang/String;I)V;                                                                                  
const SI-29 = Asciz       this;                                                                                                    
const SI-30 = Asciz       Signature;                                                                                               
const SI-31 = Asciz       ()V;                                                                                                     
const SI-32 = Asciz       <clinit>;                                                                                                
const SI-33 = Asciz       Ljava/lang/Enum<Lcom/foocorp/AnnotationValue;>;;                                                         
const SI-34 = Asciz       SourceFile;                                                                                              
const SI-35 = Asciz       AnnotationValue.java;                                                                                    
const SI-36 = NameAndType SI-16:SI-17;//  $$VALUES:[Lcom/foocorp/AnnotationValue;                                                       
const SI-37 = class       SI-17;    //  "[Lcom/foocorp/AnnotationValue;"                                                             
const SI-38 = NameAndType SI-46:SI-47;//  clone:()Ljava/lang/Object;                                                                   
const SI-39 = Asciz       com/foocorp/AnnotationValue;                                                                             
const SI-40 = NameAndType SI-22:SI-48;//  valueOf:(Ljava/lang/Class;Ljava/lang/String;)Ljava/lang/Enum;                                
const SI-41 = NameAndType SI-27:SI-28;//  "<init>":(Ljava/lang/String;I)V                                                              
const SI-42 = NameAndType SI-27:SI-28;//  "<init>":(Ljava/lang/String;I)V                                                              
const SI-43 = NameAndType SI-14:SI-15;//  MEMBER:Lcom/foocorp/AnnotationValue;                                                         
const SI-44 = Asciz       java/lang/Enum;                                                                                          
const SI-45 = Asciz       com/foocorp/AnnotationValue$$Annotation;                                                                  
const SI-46 = Asciz       clone;                                                                                                   
const SI-47 = Asciz       ()Ljava/lang/Object;;                                                                                    
const SI-48 = Asciz       (Ljava/lang/Class;Ljava/lang/String;)Ljava/lang/Enum;;                                                   

{
public static final com.foocorp.AnnotationValue MEMBER;

private static final com.foocorp.AnnotationValue[] $$VALUES;

public static com.foocorp.AnnotationValue[] values();
  Code:                                              
   Stack=1, Locals=0, Args_size=0                    
   0:   getstatic       SI-1; //Field $$VALUES:[Lcom/foocorp/AnnotationValue;
   3:   invokevirtual   SI-2; //Method "[Lcom/foocorp/AnnotationValue;".clone:()Ljava/lang/Object;
   6:   checkcast       SI-3; //class "[Lcom/foocorp/AnnotationValue;"                            
   9:   areturn                                                                                 
  LineNumberTable:                                                                              
   line 6: 0                                                                                    


public static com.foocorp.AnnotationValue valueOf(java.lang.String);
  Code:
   Stack=2, Locals=1, Args_size=1
   0:   ldc_w   SI-4; //class com/foocorp/AnnotationValue
   3:   aload_0
   4:   invokestatic    SI-5; //Method java/lang/Enum.valueOf:(Ljava/lang/Class;Ljava/lang/String;)Ljava/lang/Enum;
   7:   checkcast       SI-4; //class com/foocorp/AnnotationValue
   10:  areturn
  LineNumberTable:
   line 6: 0

  LocalVariableTable:
   Start  Length  Slot  Name   Signature
   0      11      0    name       Ljava/lang/String;


private com.foocorp.AnnotationValue(java.lang.String, int);
  Code:
   Stack=3, Locals=3, Args_size=3
   0:   aload_0
   1:   aload_1
   2:   iload_2
   3:   invokespecial   SI-6; //Method java/lang/Enum."<init>":(Ljava/lang/String;I)V
   6:   return
  LineNumberTable:
   line 6: 0
   line 9: 6

  LocalVariableTable:
   Start  Length  Slot  Name   Signature
   0      7      0    this       Lcom/foocorp/AnnotationValue;

  Signature: length = 0x2
   00 1F

static {};
  Code:
   Stack=4, Locals=0, Args_size=0
   0:   new     SI-4; //class com/foocorp/AnnotationValue
   3:   dup
   4:   ldc     SI-7; //String MEMBER
   6:   iconst_0
   7:   invokespecial   SI-8; //Method "<init>":(Ljava/lang/String;I)V
   10:  putstatic       SI-9; //Field MEMBER:Lcom/foocorp/AnnotationValue;
   13:  iconst_1
   14:  anewarray       SI-4; //class com/foocorp/AnnotationValue
   17:  dup
   18:  iconst_0
   19:  getstatic       SI-9; //Field MEMBER:Lcom/foocorp/AnnotationValue;
   22:  aastore
   23:  putstatic       SI-1; //Field $$VALUES:[Lcom/foocorp/AnnotationValue;
   26:  return
  LineNumberTable:
   line 7: 0
   line 6: 13


}
{code}


javap -private -verbose output for eclipse-compiled version:

{code}
Compiled from "AnnotationValue.java"         
public final class com.foocorp.AnnotationValue extends java.lang.Enum
  SourceFile: "AnnotationValue.java"                                 
  Signature: length = 0x2                                            
   00 29                                                             
  InnerClass:                                                        
   public abstract SI-45= SI-43 of SI-1; //Annotation=class com/foocorp/AnnotationValue$$Annotation of class com/foocorp/AnnotationValue
  minor version: 0                                                                                                               
  major version: 49                                                                                                              
  Constant pool:                                                                                                                 
const SI-1 = class        SI-2;     //  com/foocorp/AnnotationValue                                                                  
const SI-2 = Asciz        com/foocorp/AnnotationValue;                                                                             
const SI-3 = class        SI-4;     //  java/lang/Enum                                                                               
const SI-4 = Asciz        java/lang/Enum;                                                                                          
const SI-5 = Asciz        MEMBER;                                                                                                  
const SI-6 = Asciz        Lcom/foocorp/AnnotationValue;;                                                                           
const SI-7 = Asciz        ENUM$$VALUES;                                                                                             
const SI-8 = Asciz        [Lcom/foocorp/AnnotationValue;;                                                                          
const SI-9 = Asciz        <clinit>;                                                                                                
const SI-10 = Asciz       ()V;                                                                                                     
const SI-11 = Asciz       Code;                                                                                                    
const SI-12 = String      SI-5;     //  MEMBER                                                                                       
const SI-13 = Method      SI-1.SI-14; //  com/foocorp/AnnotationValue."<init>":(Ljava/lang/String;I)V                                  
const SI-14 = NameAndType SI-15:SI-16;//  "<init>":(Ljava/lang/String;I)V                                                              
const SI-15 = Asciz       <init>;                                                                                                  
const SI-16 = Asciz       (Ljava/lang/String;I)V;                                                                                  
const SI-17 = Field       SI-1.SI-18; //  com/foocorp/AnnotationValue.MEMBER:Lcom/foocorp/AnnotationValue;                             
const SI-18 = NameAndType SI-5:SI-6;//  MEMBER:Lcom/foocorp/AnnotationValue;                                                           
const SI-19 = Field       SI-1.SI-20; //  com/foocorp/AnnotationValue.ENUM$$VALUES:[Lcom/foocorp/AnnotationValue;                       
const SI-20 = NameAndType SI-7:SI-8;//  ENUM$$VALUES:[Lcom/foocorp/AnnotationValue;                                                     
const SI-21 = Asciz       LineNumberTable;                                                                                         
const SI-22 = Asciz       LocalVariableTable;                                                                                      
const SI-23 = Method      SI-3.SI-14; //  java/lang/Enum."<init>":(Ljava/lang/String;I)V                                               
const SI-24 = Asciz       this;                                                                                                    
const SI-25 = Asciz       values;                                                                                                  
const SI-26 = Asciz       ()[Lcom/foocorp/AnnotationValue;;                                                                        
const SI-27 = Method      SI-28.SI-30;        //  java/lang/System.arraycopy:(Ljava/lang/Object;ILjava/lang/Object;II)V                
const SI-28 = class       SI-29;    //  java/lang/System                                                                             
const SI-29 = Asciz       java/lang/System;                                                                                        
const SI-30 = NameAndType SI-31:SI-32;//  arraycopy:(Ljava/lang/Object;ILjava/lang/Object;II)V                                         
const SI-31 = Asciz       arraycopy;                                                                                               
const SI-32 = Asciz       (Ljava/lang/Object;ILjava/lang/Object;II)V;                                                              
const SI-33 = Asciz       valueOf;                                                                                                 
const SI-34 = Asciz       (Ljava/lang/String;)Lcom/foocorp/AnnotationValue;;                                                       
const SI-35 = Method      SI-3.SI-36; //  java/lang/Enum.valueOf:(Ljava/lang/Class;Ljava/lang/String;)Ljava/lang/Enum;                 
const SI-36 = NameAndType SI-33:SI-37;//  valueOf:(Ljava/lang/Class;Ljava/lang/String;)Ljava/lang/Enum;                                
const SI-37 = Asciz       (Ljava/lang/Class;Ljava/lang/String;)Ljava/lang/Enum;;                                                   
const SI-38 = Asciz       SourceFile;                                                                                              
const SI-39 = Asciz       AnnotationValue.java;                                                                                    
const SI-40 = Asciz       Signature;                                                                                               
const SI-41 = Asciz       Ljava/lang/Enum<Lcom/foocorp/AnnotationValue;>;;                                                         
const SI-42 = Asciz       InnerClasses;                                                                                            
const SI-43 = class       SI-44;    //  com/foocorp/AnnotationValue$$Annotation                                                       
const SI-44 = Asciz       com/foocorp/AnnotationValue$$Annotation;                                                                  
const SI-45 = Asciz       Annotation;                                                                                              

{
public static final com.foocorp.AnnotationValue MEMBER;

private static final com.foocorp.AnnotationValue[] ENUM$$VALUES;

static {};
  Code:   
   Stack=4, Locals=0, Args_size=0
   0:   new     SI-1; //class com/foocorp/AnnotationValue
   3:   dup                                            
   4:   ldc     SI-12; //String MEMBER                   
   6:   iconst_0                                       
   7:   invokespecial   SI-13; //Method "<init>":(Ljava/lang/String;I)V
   10:  putstatic       SI-17; //Field MEMBER:Lcom/foocorp/AnnotationValue;
   13:  iconst_1                                                         
   14:  anewarray       SI-1; //class com/foocorp/AnnotationValue          
   17:  dup                                                              
   18:  iconst_0                                                         
   19:  getstatic       SI-17; //Field MEMBER:Lcom/foocorp/AnnotationValue;
   22:  aastore                                                          
   23:  putstatic       SI-19; //Field ENUM$$VALUES:[Lcom/foocorp/AnnotationValue;
   26:  return                                                                 
  LineNumberTable:                                                             
   line 7: 0                                                                   
   line 6: 13



private com.foocorp.AnnotationValue(java.lang.String, int);
  Code:
   Stack=3, Locals=3, Args_size=3
   0:   aload_0
   1:   aload_1
   2:   iload_2
   3:   invokespecial   SI-23; //Method java/lang/Enum."<init>":(Ljava/lang/String;I)V
   6:   return
  LineNumberTable:
   line 6: 0

  LocalVariableTable:
   Start  Length  Slot  Name   Signature
   0      7      0    this       Lcom/foocorp/AnnotationValue;


public static com.foocorp.AnnotationValue[] values();
  Code:
   Stack=5, Locals=3, Args_size=0
   0:   getstatic       SI-19; //Field ENUM$$VALUES:[Lcom/foocorp/AnnotationValue;
   3:   dup
   4:   astore_0
   5:   iconst_0
   6:   aload_0
   7:   arraylength
   8:   dup
   9:   istore_1
   10:  anewarray       SI-1; //class com/foocorp/AnnotationValue
   13:  dup
   14:  astore_2
   15:  iconst_0
   16:  iload_1
   17:  invokestatic    SI-27; //Method java/lang/System.arraycopy:(Ljava/lang/Object;ILjava/lang/Object;II)V
   20:  aload_2
   21:  areturn
  LineNumberTable:
   line 1: 0



public static com.foocorp.AnnotationValue valueOf(java.lang.String);
  Code:
   Stack=2, Locals=1, Args_size=1
   0:   ldc     SI-1; //class com/foocorp/AnnotationValue
   2:   aload_0
   3:   invokestatic    SI-35; //Method java/lang/Enum.valueOf:(Ljava/lang/Class;Ljava/lang/String;)Ljava/lang/Enum;
   6:   checkcast       SI-1; //class com/foocorp/AnnotationValue
   9:   areturn
  LineNumberTable:
   line 1: 0



}
{code}

Iulian, reassigning to you, since you have experience with SI-1879.
This is probably a duplicate of SI-1879. Please check the discussion there. Closing this as a duplicate.
