The following code give this error when written in scala (while deploying) :

```scala
org.hibernate.MappingException: Could not determine type for: GUID, at table: COM_MAPPING, for columns: [org.hibernate.mapping.Column(modified_by)]
```

but not when written in Java, I assume the annotations are improperly handled by the compiler and thus at runtime hibernate gets confused. I tried several versions of Hibernate too (before I tried coding it in Java) and this happened with all the ones I tried (3.x). Here is the (simplified) Scala code :

// Scala Start ----------------------------------------------------------------------
```scala
@MappedSuperclass
@TypeDef(name="GUID",typeClass=classOf[com.toto.persistence.GUIDAsStringType])
trait RefDataEntity {

  @Id
  @Type(`type`="GUID")
  @Column(name="id", nullable=false)
  @BeanProperty
  var id : GUID = null;

  @Column(name="short_code", nullable=false, unique=true)
  @BeanProperty
  var shortCode : String = null;

  @Type(`type`="GUID")
  @Column(name="modified_by", nullable=false)
  @BeanProperty
  var modifiedBy : GUID = null;
}
```

```scala
@Entity()
@Table(name="COM_MAPPING")
@NamedQueries(Array(
  new NamedQuery(name="ComEntity.FindAll", query="SELECT e FROM ComEntity e"),
  new NamedQuery(name="ComEntity.FindByShortCode", query="SELECT e FROM ComEntity e WHERE e.shortCode = :shortCode")))
class ComEntity extends RefDataEntity {

  @Column(name="com_name", nullable=false)
  @BeanProperty
  var comName : String = null
}

object ComEntity {

  object QueryNames {

    val FIND_ALL = "ComEntity.FindAll"
    val FIND_BY_SHORT_CODE = "ComEntity.FindByShortCode"
  }
}
```

```scala
@Entity()
@Table(name="CUR_MAPPING")
@NamedQueries(Array(
  new NamedQuery(name="CurEntity.FindAll", query="SELECT e FROM CurEntity e"),
  new NamedQuery(name="CurEntity.FindByShortCode", query="SELECT e FROM CurEntity e WHERE e.shortCode = :shortCode")))
class CurEntity extends RefDataEntity {

  @Column(name="cur_name", nullable=false)
  @BeanProperty
  var curName : String = null
}

object CurEntity {

  object QueryNames {

    val FIND_ALL = "CurEntity.FindAll"
    val FIND_BY_SHORT_CODE = "CurEntity.FindByShortCode"
  }
}
```
// Scala End --------------------------------------------------------------------------

And the Java code that does work:

// Java Begin --------------------------------------------------------------------------
```scala
@MappedSuperclass
@TypeDef(name = "GUID", typeClass = com.toto.persistence.GUIDAsStringType.class)
public abstract class RefDataEntityJ {

    @Id
    @Type(type = "GUID")
    @Column(name = "id", nullable = false)
    public GUID id = null;

    @Column(name = "short_code", nullable = false, unique = true)
    public String shortCode = null;

    @Type(type = "GUID")
    @Column(name = "modified_by", nullable = false)
    public GUID modifiedBy = null;

    public GUID getId() {
        return id;
    }

    public void setId(GUID id) {
        this.id = id;
    }

    public String getShortCode() {
        return shortCode;
    }

    public void setShortCode(String shortCode) {
        this.shortCode = shortCode;
    }

    public GUID getModifiedBy() {
        return modifiedBy;
    }

    public void setModifiedBy(GUID modifiedBy) {
        this.modifiedBy = modifiedBy;
    }
}
```

```scala
@Entity()
@Table(name = "COM_MAPPING")
@NamedQueries({
        @NamedQuery(name = "ComEntity.FindAll", query = "SELECT e FROM ComEntityJ e"),
        @NamedQuery(name = "ComEntity.FindByShortCode", query = "SELECT e FROM ComEntityJ e WHERE e.shortCode = :shortCode")})
public class ComEntityJ extends RefDataEntityJ {

    public interface QueryNames {

        public final String FIND_ALL = "ComEntity.FindAll";
        public final String FIND_BY_SHORT_CODE = "ComEntity.FindByShortCode";
    }

    @Column(name = "com_name", nullable = false)
    public String comName = null;

    public String getComName() {
        return comName;
    }

    public void setComName(String comName) {
        this.comName = comName;
    }
}
```

```scala
@Entity()
@Table(name = "CUR_MAPPING")
@NamedQueries({
        @NamedQuery(name = "CurEntity.FindAll", query = "SELECT e FROM CurEntityJ e"),
        @NamedQuery(name = "CurEntity.FindByShortCode", query = "SELECT e FROM CurEntityJ e WHERE e.shortCode = :shortCode")})
public class CurEntityJ extends RefDataEntityJ {

    public interface QueryNames {

        public final String FIND_ALL = "CurEntity.FindAll";
        public final String FIND_BY_SHORT_CODE = "CurEntity.FindByShortCode";
    }

    @Column(name = "cur_name", nullable = false)
    public String curName = null;

    public String getCurName() {
        return curName;
    }

    public void setCurName(String curName) {
        this.curName = curName;
    }
}
```
// Java End --------------------------------------------------------------------------
That implies it has nothing to do with java/scala or the annotations, but with the trait encoding.  I don't know anything about hibernate, but when you write "trait RefDataEntity" its implementations will be in "class RefDataEntity$class".  Can you compare the bytecode for "abstract class RefDataEntity" to the bytecode of RefDataEntity and RefDataEntity$class when you make it a trait? Because whatever differs there should illuminate the issue.

I'm guessing the implementation methods in RefDataEntity$class have the annotation, but concrete classes which extend the trait are given forwarders which probably do not.
The trait version ComEntity's getId()'s bytecode is:

```scala
0 aload_0
1 invokestatic #32 <com/toto/RefDataEntity$class.getId>
4 areturn
```

and it's id() like so:

```scala
0 aload_0
1 getfield #23 <com/toto/ComEntity.id>
4 areturn
```

and the trait's RefDataEntity$class's getId()'s like so (it has no id()):

```scala
0 aload_0
1 invokeinterface #21 <com/toto/RefDataEntity.id> count 1
6 areturn
```

While the abstract version's ComEntity has no mention of id/getId (since it uses it's parents), and the RefDataEntity's getId():

```scala
0 aload_0
1 invokevirtual #26 <com/toto/RefDataEntity.id>
4 areturn
```

and the id():

```scala
0 aload_0
1 getfield #20 <com/toto/RefDataEntity.id>
4 areturn
```

The abstract RefDataEntity class has the TypeDef annotation visible and it defines the methods there, which the child inherits, thus it is visible and poses no problems. In the trait version however, the child doesn't inherit those methods but implements them (since it uses the RefDataEntity trait) and the class does not have the annotations in it, which is why at runtime it gets confused. That is how I understand it from looking at it with jclasslib, but I've been using scala for 2 months only.
From what we currently understand we cannot go forward with this ticket. What we really need is a minimized example, showing the undesired / missing behavior, and a clear statement of what the desired result is.

More concretely, I can't see what annotations are needed in which classfile and on which method precisely. We need something along the lines "compile trait X and class Y extending X, and obtain classfiles X and X$class and Y. we need annotation a on method m in classfile C, but it's not there".

Then we can discuss how it is possible to get there. Saying "it doesn't work with hibernate" is not enough, our knowledge of hibernate is close to zero.
