The following code when compiled with Scala version 2.9.0-1 yields a different bytecode when compared to previous versions.

```scala
final class AtomTest(vIn:Int) {
      final val v = vIn       
      def square = v*v
}
```

For the method "square":
Scala 2.7.7 and 2.8.1 with -optimise :
```scala
public int square();
  Code:
   0:   aload_0
   1:   getfield        #12; //Field v:I
   4:   aload_0
   5:   getfield        #12; //Field v:I
   8:   imul
   9:   ireturn
```

Scala 2.9.0-1 with -optimise:
```scala
public int square();
  Code:
   0:   aload_0
   1:   invokevirtual   #14; //Method v:()I
   4:   aload_0
   5:   invokevirtual   #14; //Method v:()I
   8:   imul
   9:   ireturn
```

Note that invokevirtual is now being generated for field access.

I don't have a benchmark to prove that this degrades performance, for two reasons:
- A simple one class benchmark will get instantly optimised by JIT and will not show any degradation
- I have some production code which does run slowly with Scala 2.9.0-1 but there might be other factors affecting the performance of that code. For example, there seems to be a known degradation in Hashset addition method which my production code uses frequently.
When targeting Android, Iulian suggested on the mailing list that ProGuard should be able to inline the getter. But I am not able to get ProGuard to do so.

{code:title=invokeVirtual.scala|borderStyle=solid}
package com.test.invoke

final class AtomTest(vIn:Int) {
  final val v = vIn

  def square = v*v
}
```scala


{code:title=Run compiler|borderStyle=solid}
/opt/scala-2.9.0.1/bin/scalac -d outDir -optimize invokeVirtual.scala
```


{code:title=Run ProGuard|borderStyle=solid}
$JAVA_HOME/bin/java -jar ~/tmp/co/proguard4.6/lib/proguard.jar 
  -injars outDir 
  -libraryjars /opt/scala-2.9.0.1/lib/scala-library.jar
  -libraryjars $JAVA_HOME/jre/lib/rt.jar
  -keep "class com.test.invoke.* {public <methods>;}"
  -outjars invokeVirtual.jar
  -optimizationpasses 2
```scala


{code:title=Disassembly|borderStyle=solid}
javap -classpath invokeVirtual.jar -c com.test.invoke.AtomTest
public final int square();
  Code:
   0:   aload_0
   1:   invokevirtual   #5; //Method v:()I
   4:   aload_0
   5:   invokevirtual   #5; //Method v:()I
   8:   imul
   9:   ireturn


```
