{code}
trait Base[B] {
  def data: AnyRef;
}

class Sub1[@specialized B](override val data: Array[B]) extends Base[B] {  
  assert(data != null)
}

class Sub2[@specialized B](override val data: Option[B]) extends Base[B] {  
  assert(data != null)
}

class M[@specialized A]

class Sub3[@specialized B](override val data: M[B]) extends Base[B] {  
  assert(data != null)
}

object Test extends Application {
  new Sub1[String](Array("")) // okay
  new Sub1[Int](Array(0))     // assertion failed
  
  new Sub2[Int](Some(0))      // okay
  
  new Sub3[Int](new M[Int])   // assertion failed
}
{code} 

What versions of the following are you using?
Scala: 2.8.1
Java: 1.6

I believe that the reason the first one fails is because the ctor in `Sub1` uses its argument instead of the call to `data()` accessor method to obtain the value of the `data` field:


{code}
...
   9:	getstatic	SI-33; //Field scala/Predef$$.MODULE$$:Lscala/Predef$$;
   12:	aload_1
   13:	ifnonnull	20
   16:	iconst_0
   17:	goto	21
   20:	iconst_1
   21:	invokevirtual	SI-37; //Method scala/Predef$$.assert:(Z)V
   24:	return
...
{code}
(In r24400) Fixes and closes SI-4013.

No review.
