=== What steps will reproduce the problem (please be specific and use wikiformatting)? ===
{code}
  trait A

  class B(val x: Int) {
    self: A =>

    def this() = this()
  }

  val x = new B(2) with A
  val y = new B with A
{code} 
and also
{code}
  trait A

  class B {
    self: A =>

    def this(x: Int) = this()
  }

  val x = new B(2) with A
  val y = new B with A
{code}


=== What is the expected behavior? ===
Since
{{val x = new B(1,2) with A}}
gives
compile error:
{code}
error: overloaded method constructor B with alternatives:
  (x: Int)B <and>
  ()B
 cannot be applied to (Int, Int)
       val x = new B(1,2) with A
                   ^
{code}
Either a class using the overloaded constructor or compile-time error (rather than runtime)


=== What do you see instead? ===
Runtime error!
{code}
java.lang.VerifyError: (class: B, method: <init> signature: ()V) Expecting to find unitialized object on stack
{code}

=== What versions of the following are you using? ===
  - Scala: 2.8.1 and 2.9.0RC1
  - Java: 1.6.0.24
  - Operating system: Ubuntu/scalabot
The problem is the {{def this() = this()}}. Removing it  does away with the {{VerifyError}}. 

Rephrasing the example: 

{code}
trait A

class B(val x: Int) {
  self: A =>

  def this() = this()
}

object C extends B(2) with A  {
  def main(args: Array[String]) {  }
}
{code}

we get the runtime error: 

{code}
C:\temp\>java -verify -Xbootclasspath/a:Z:\scala-library.jar C
Exception in thread "main" java.lang.VerifyError: (class: B, method: <init> signature: ()V) Expecting to find unitialized object on stack
        at C.main(bt4.scala)
{code}


Regarding classfile {{B}}, the difference between including or not {{def this() = this()}} is the {{public B();}} below:

{code}
C:\temp\>javap -c B
Compiled from "bt4.scala"
public class B extends java.lang.Object implements scala.ScalaObject{
public int x();
  // omitted 

public B(int);
  // omitted 

public B();
  Code:
   0:   getstatic       SI-27; //Field scala/Predef$$.MODULE$$:Lscala/Predef$$;
   3:   invokespecial   SI-28; //Method scala/Predef$$."<init>":()V
   6:   return

}
{code}

Classfile {{C}} (with or without {{def this() = this()}}) is: 


{code}
C:\temp\>javap -c C
Compiled from "bt4.scala"
public final class C extends java.lang.Object{
public static final void main(java.lang.String[]);
  Code:
   0:   getstatic       SI-11; //Field C$$.MODULE$$:LC$$;
   3:   aload_0
   4:   invokevirtual   SI-13; //Method C$$.main:([Ljava/lang/String;)V
   7:   return

public static final int x();
  Code:
   0:   getstatic       SI-11; //Field C$$.MODULE$$:LC$$;
   3:   invokevirtual   SI-17; //Method C$$.x:()I
   6:   ireturn

}
{code}
