In the Java code below
{noformat}
class ImageView { 
    void setTag(Object o) {} 
} 
class Test1 { 
    void foo() { 
        ImageView imageView = null; 
        imageView.setTag(null); 
    } 
} 
{noformat}
method {{foo}} is translated into the following bytecode
{noformat}
void foo();
  Code:
   Stack=2, Locals=2, Args_size=1
   0:	aconst_null
   1:	astore_1
   2:	aload_1
   3:	aconst_null
   4:	invokevirtual	#2; //Method ImageView.setTag:(Ljava/lang/Object;)V
   7:	return
{noformat}
while in Scala
{noformat}
class ImageView {
  def setTag(o: AnyRef) {}
}
class Test {
  def foo {
    var imageView: ImageView = null
    imageView setTag null
  }
}
{noformat}
the generated code (2.9.x and trunk) for method {{foo}} looks as follows:
{noformat}
public void foo();
  Code:
   Stack=2, Locals=2, Args_size=1
   0:	aconst_null
   1:	pop
   2:	aconst_null
   3:	astore_1
   4:	aload_1
   5:	aconst_null
   6:	pop
   7:	aconst_null
   8:	invokevirtual	#12; //Method ImageView.setTag:(Ljava/lang/Object;)V
   11:	return
{noformat}
Instructions on lines 0,1,5,6 are superfluous.

This is fixed in 2.11 with the default (GenASM) backend:

{noformat}
public void foo();
    Code:
       0: aconst_null   
       1: astore_1      
       2: aload_1       
       3: aconst_null   
       4: invokevirtual #16                 // Method ImageView.setTag:(Ljava/lang/Object;)V
       7: return
{noformat}

The problem is still there when using GenBCode, though.
