Implementing a specialized method with a synchronized block generates an improperly synchronized classfile. This only applies to whole-method synchronization, where the compiler emits the ACC_SYNCHRONIZED flag instead of generating explicit monitor code.

```scala
trait Counter[@specialized +T] {
  def apply(): T
}

class IntCounter(var state: Int) extends Counter[Int] {
  def apply(): Int = synchronized { // not properly synchronized
    val n = state
    state += 1
    n
  }
}
```

```scala
Compiled from "Counter.scala"
public class IntCounter implements Counter$mcI$sp {
  private int state;

  // (snip)

  // Clear ACC_SYNCHRONIZED here
  public synchronized int apply();
    Code:
       0: aload_0       
       1: invokevirtual #66 // Method apply$mcI$sp:()I
       4: ireturn       

  // Set ACC_SYNCHRONIZED here
  public int apply$mcI$sp();
    Code:
       0: aload_0       
       1: invokevirtual #68 // Method state:()I
       4: istore_1      
       5: aload_0       
       6: aload_0       
       7: invokevirtual #68 // Method state:()I
      10: iconst_1      
      11: iadd          
      12: invokevirtual #70 // Method state_$eq:(I)V
      15: iload_1       
      16: ireturn       

  // Nix ACC_SYNCHRONIZED here as well
  public synchronized java.lang.Object apply();
    Code:
       0: aload_0       
       1: invokevirtual #74 // Method apply:()I
       4: invokestatic  #80 // Method scala/runtime/BoxesRunTime.boxToInteger:(I)Ljava/lang/Integer;
       7: areturn       

  // (snip)
}
```
