By way of example:

{code}
object TestMe {
  def returnsPrimitive(x: Int): Int = x

  def testme() {
    val nonTrivialCondition = 42
    if (nonTrivialCondition == 42) {
      returnsPrimitive(5)
    }
    else {
      Unit
    }
    Unit
  }
}
{code}

Even though the value of the if-then-else branch is unused, it boxes the integer returned by returnsPrimitive().

{code}
public void testme();
    flags: ACC_PUBLIC
    Code:Bug
      stack=2, locals=2, args_size=1
         0: bipush        42
         2: istore_1      
         3: iload_1       
         4: bipush        42
         6: if_icmpne     20
         9: aload_0       
        10: iconst_5      
        11: invokevirtual #22                 // Method returnsPrimitive:(I)I
        14: invokestatic  #28                 // Method scala/runtime/BoxesRunTime.boxToInteger:(I)Ljava/lang/Integer;
        17: goto          23
        20: getstatic     #33                 // Field scala/Unit$.MODULE$:Lscala/Unit$;
        23: pop           
        24: getstatic     #33                 // Field scala/Unit$.MODULE$:Lscala/Unit$;
        27: pop           
        28: return        
      LineNumberTable:
        line 14: 0
        line 15: 3
        line 16: 9
        line 19: 20
        line 15: 23
        line 21: 24
      LocalVariableTable:
        Start  Length  Slot  Name   Signature
               0      29     0  this   Lfast/TestMe$;
               3      25     1 nonTrivialCondition   I
{code}

Presumably, this boxing could be eliminated?
This is not related to specialization. 

The root of the problem is stack discipline: the if expression leaves an Int on the stack for the true branch and Unit for the false branch. They're common supertype is Any, which is erased to Object: so there you have it, to put an I onto an Ljava.lang.Object stack slot you need boxing.

{code}
/* val resultOfIfExpression: Any = */ 
  if (nonTrivialCondition == 42) {
    returnsPrimitive(5) // put resultOfIfExpression: Any = Integer(returnsPrimitive(5))
  } else {
    Unit                // put resultOfIfExpression: Any = Unit
  }
{code}

This could certainly be improved (-optimize doesn't help here) but it's not a blocker. With GenBCode just around the corner, it may be best if Miguel has a look.
Btw, replacing the Unit with 0 or removing the false branch altogether eliminates the boxing:
{code}
  if (nonTrivialCondition == 42) {
    returnsPrimitive(5)
  } else {
    0
  }
{code}
OR
{code}
  if (nonTrivialCondition == 42) {
    returnsPrimitive(5)
  }
{code}

yields:

{code}
  public void testme();
    Code:
       0: bipush        42
       2: bipush        42
       4: if_icmpne     15
       7: aload_0       
       8: iconst_5      
       9: invokevirtual #20                 // Method returnsPrimitive:(I)I
      12: goto          16
      15: iconst_0      
      16: pop           
      17: getstatic     #25                 // Field scala/Unit$.MODULE$:Lscala/Unit$;
      20: pop           
      21: return  
{code}
I should point out that it's unlikely that you meant to refer to {{Unit}} in the else branch, and probably meant:

{code}
  if (nonTrivialCondition == 42) {
    returnsPrimitive(5)
  } else {
    ()
  }
{code}

In such code, no boxing is incurred under {{-optimize}}, test case: https://github.com/retronym/scala/compare/ticket/6527
