It would save 6 chars if we had an implicit conversion from BooleanSetting to Boolean.
https://github.com/scala/scala/pull/2272

Save a few bytes, spend a few bytes.

This isn't news; I just wanted to see if the #devWarning syntax worked.

{code}
scala> :javap build/quick/classes/compiler/scala/tools/nsc/Global.class#devWarning
  public final void devWarning(scala.Function0<java.lang.String>);
    flags: ACC_PUBLIC, ACC_FINAL
    Code:
      stack=5, locals=2, args_size=2
         0: getstatic     #1296               // Field scala/tools/nsc/settings/AbsScalaSettings$.MODULE$:Lscala/tools/nsc/settings/AbsScalaSettings$;
         3: aload_0      
         4: invokevirtual #1219               // Method settings:()Lscala/tools/nsc/Settings;
         7: invokeinterface #1312,  1         // InterfaceMethod scala/tools/nsc/settings/ScalaSettings.developer:()Lscala/tools/nsc/settings/MutableSettings$BooleanSetting;
        12: invokevirtual #1305               // Method scala/tools/nsc/settings/AbsScalaSettings$.valueOfBooleanSetting:(Lscala/tools/nsc/settings/AbsSettings$AbsSetting;)Z
        15: ifne          36
        18: getstatic     #1296               // Field scala/tools/nsc/settings/AbsScalaSettings$.MODULE$:Lscala/tools/nsc/settings/AbsScalaSettings$;
        21: aload_0      
        22: invokevirtual #1219               // Method settings:()Lscala/tools/nsc/Settings;
        25: invokeinterface #1301,  1         // InterfaceMethod scala/tools/nsc/settings/ScalaSettings.debug:()Lscala/tools/nsc/settings/MutableSettings$BooleanSetting;
        30: invokevirtual #1305               // Method scala/tools/nsc/settings/AbsScalaSettings$.valueOfBooleanSetting:(Lscala/tools/nsc/settings/AbsSettings$AbsSetting;)Z
{code}
Not really a big trouble, but it doesn't look like {{@inline}} worked.
The supersessive PR:  https://github.com/scala/scala/pull/2327

That may not be a word sanctioned by the dictionary.
