The following code crashes the compiler:

```scala
object Example extends App {
  type Tag[X] = {type Tag = X}
  type TaggedArray[T] = Array[T] with Tag[Any]

  def method[T: reflect.ClassTag](a: TaggedArray[T], value: T) {a.update(0, value)}

  method(Array(1, 2).asInstanceOf[TaggedArray[Int]], 1)
}
```

Sympton:
[error] uncaught exception during compilation: RuntimeException("scala.Array.update : Object, Object, Any") @ scala.sys.
package$.error(package.scala:27)
java.lang.RuntimeException: scala.Array.update : Object, Object, Any
        at scala.sys.package$.error(package.scala:27)
        at scala.tools.nsc.backend.ScalaPrimitives$$anonfun$elementType$1$1$$anonfun$apply$1.apply(ScalaPrimitives.scala
:571)
        at scala.tools.nsc.backend.ScalaPrimitives$$anonfun$elementType$1$1.apply(ScalaPrimitives.scala:571)
        at scala.tools.nsc.backend.ScalaPrimitives$$anonfun$elementType$1$1.apply(ScalaPrimitives.scala:567)
        at scala.reflect.internal.SymbolTable.enteringPhase(SymbolTable.scala:203)
        at scala.tools.nsc.backend.ScalaPrimitives.elementType$1(ScalaPrimitives.scala:567)
        at scala.tools.nsc.backend.ScalaPrimitives.getPrimitive(ScalaPrimitives.scala:592)
        at scala.tools.nsc.backend.icode.GenICode$ICodePhase.genPrimitiveOp(GenICode.scala:421)
        at scala.tools.nsc.backend.icode.GenICode$ICodePhase.genLoadApply6$1(GenICode.scala:751)


My theory is that the presence of the "with Tag" on the Array type disrupts the usual process of resolving the correct primitive type when generating operations on the Array.

Note this is the (greatly simplified) cause of #6975, which I reported. I will close the other issue now.
Actually, measurements on 2.11-SNAPSHOT suggest that neither tagged primitive arrays (Array[Int] with Tag), nor arrays of tagged primitives (eg Array[Int with Tag]), are boxed :)

(The -optimise flag is required to Scalac).

object TaggedArray {
  val tagary: Array[Int] with Tag = Array(1).asInstanceOf[Array[Int] with Tag]
  tagary.update(0, 7)
  println(tagary(0))
}
{code}
scala> :javap -cp test.TaggedArray$
Compiled from "Primitive.scala"
public final class test.TaggedArray$ {
  public static final test.TaggedArray$ MODULE$;

  private final int[] tagary;
 [..snip..]
  private test.TaggedArray$();
    Code:
       0: aload_0
       1: invokespecial #19                 // Method java/lang/Object."<init>":()V
       4: aload_0
       5: putstatic     #21                 // Field MODULE$:Ltest/TaggedArray$;
       8: aload_0
       9: iconst_1
      10: newarray       int
      12: dup
      13: iconst_0
      14: iconst_1
      15: iastore
      16: putfield      #17                 // Field tagary:[I
      19: aload_0
      20: invokevirtual #23                 // Method tagary:()[I
      23: iconst_0
      24: bipush        7
      26: iastore
      27: getstatic     #28                 // Field scala/Predef$.MODULE$:Lscala/Predef$;
      30: aload_0
      31: invokevirtual #23                 // Method tagary:()[I
      34: iconst_0
      35: iaload
      36: invokestatic  #34                 // Method scala/runtime/BoxesRunTime.boxToInteger:(I)Ljava/lang/Integer;
      39: invokevirtual #38                 // Method scala/Predef$.println:(Ljava/lang/Object;)V
      42: return
}}}

