{code}
scala> class Wrapper[Repr](val xs: Repr) extends AnyVal
defined class Wrapper

scala> new Wrapper(new Array[Int](1))
java.lang.ClassCastException: [Ljava.lang.Object; cannot be cast to [Ljava.lang.Integer;
	at .<init>(<console>:9)
	at .<clinit>(<console>)
	at .<init>(<console>:7)
	at .<clinit>(<console>)
	at $print(<console>)
{code}

Similarly:

{code}
scala> class Wrap[Repr](val xs: Repr) extends AnyVal
defined class Wrap

scala> implicit class ops[Repr](val xs: Repr) extends AnyVal { def toWrap = new Wrap(xs) }
defined class ops

scala> (new Array[Int](1)).toWrap
java.lang.ClassCastException: [I cannot be cast to [Ljava.lang.Integer;
	at .<init>(<console>:9)
	at .<clinit>(<console>)
	at .<init>(<console>:7)
	at .<clinit>(<console>)
	at $print(<console>)
{code}

Note the primitive array being cast in the second example.

{code}
scala> class C { new Wrapper(new Array[Int](0)) }
defined class C

scala> :javap -v C
...
{
public C();
  Code:
   Stack=2, Locals=1, Args_size=1
   0:	aload_0
   1:	invokespecial	#9; //Method java/lang/Object."<init>":()V
   4:	getstatic	#15; //Field scala/runtime/ScalaRunTime$.MODULE$:Lscala/runtime/ScalaRunTime$;
   7:	iconst_0
   8:	newarray int
   10:	invokevirtual	#19; //Method scala/runtime/ScalaRunTime$.toObjectArray:(Ljava/lang/Object;)[Ljava/lang/Object;
   13:	checkcast	#21; //class "[Ljava/lang/Integer;"
   16:	pop
   17:	return
  LocalVariableTable:
   Start  Length  Slot  Name   Signature
   0      18      0    this       LC;

  LineNumberTable:
   line 8: 0


}
{code}
Culpable code:

https://github.com/scala/scala/commit/39fc4aa84#L1R740
https://github.com/scala/scala/commit/39fc4aa84#L6R283
https://github.com/scala/scala/commit/39fc4aa84#L6R89

{code}
erasedValueClassArg(<<Wrapper[Array[Int]]>>) = Array[Integer]
{code}
This is fixed in my patch for SI-5353.
