{code}
class X {
  def f(x: String) = x

  f(null)
}
{code}

Produces the icode
{code}
  def g(): String {
  locals: 
  startBlock: 1
  blocks: [1]
  
  1: 
    7	THIS(X)
    7	CONSTANT(null)
    ?	DROP REF(class Null)
    ?	CONSTANT(null)
    7	CALL_METHOD X.f (dynamic)
    7	RETURN(REF(class String))
    
  }{code}

Note the CONSTANT(null) DROP REF(class Null) CONSTANT(NULL)

And that generates the bytecode
{code}
public java.lang.String g();
  Code:
   0:	aload_0
   1:	aconst_null
   2:	pop
   3:	aconst_null
   4:	invokevirtual	#18; //Method f:(Ljava/lang/String;)Ljava/lang/String;
   7:	areturn
{code}
Again, the redundant push null, pop, push null sequence.

For the example

{noformat}
class X {

  def f(x: String) = x

  def g { f(null) }

}
{noformat}

{{GenBCode}} emits:

{noformat}
  public void g();
    flags: ACC_PUBLIC

    Code:
      stack=2, locals=1, args_size=1
         0: aload_0       
         1: aconst_null   
         2: invokevirtual #13                 // Method f:(Ljava/lang/String;)Ljava/lang/String;
         5: pop           
         6: return        
{noformat}

Details at http://magarciaepfl.github.com/scala/

