```
~/code/scala tail sandbox/{a,b}.scala
==> sandbox/a.scala <==
  def isEmpty = value == null
  // can't seem to coerce the inliner into inlining calls to getOrElse
  // would be great if you know a way of achieving that!
  @inline final def getOrElse[B >: A](alt: => B): B = if (isEmpty) alt else value
  override def toString = if (isEmpty) "<empty>" else s"$value"
}

object Joint {
  def foo = new Optional("").getOrElse("!!!")
}

==> sandbox/b.scala <==
object Separate {
  def foo = new Optional("").getOrElse("!!!")
}
2.11.x ~/code/scala (set -x; qbin/scalac -optimize -Yinline-warnings sandbox/a.scala && qbin/scalac -optimize -Yinline-warnings sandbox/b.scala)
+ qbin/scalac -optimize -Yinline-warnings sandbox/a.scala
+ qbin/scalac -optimize -Yinline-warnings sandbox/b.scala
warning: Could not inline required method getOrElse$extension because bytecode unavailable.
warning: Could not inline required method getOrElse$extension because bytecode unavailable.
warning: At the end of the day, could not inline @inline-marked method getOrElse$extension
three warnings found
```
See also: #6723 #7393 #7685
Not sure it works for me:

```scala
package foo

final class Optional[A >: Null](val value: A) extends AnyVal {
  def get: A = value
  def isEmpty = value == null
  @inline final def getOrElse[B >: A](alt: => B): B = if (isEmpty) alt else value
}
```

```scala
package foo

class C

object Test {
  def foo: Unit = {
    val x = new Optional(null)
    println(x.getOrElse(new C))
  }
}
```

```scala
18:03 ~/Projects/211x/sandbox (2.11.x)$ scalac Macros.scala && scalac Test.scala && javap -v foo.Test$
...
  public void foo();
    flags: ACC_PUBLIC
    Code:
      stack=5, locals=2, args_size=1
         0: aconst_null
         1: astore_1
         2: getstatic     #18                 // Field scala/Predef$.MODULE$:Lscala/Predef$;
         5: getstatic     #23                 // Field foo/Optional$.MODULE$:Lfoo/Optional$;
         8: aload_1
         9: pop
        10: aconst_null
        11: new           #25                 // class foo/Test$$anonfun$foo$1
        14: dup
        15: invokespecial #26                 // Method foo/Test$$anonfun$foo$1."<init>":()V
        18: invokevirtual #30                 // Method foo/Optional$.getOrElse$extension:(Ljava/lang/Object;Lscala/Function0;)Ljava/lang/Object;
        21: invokevirtual #34                 // Method scala/Predef$.println:(Ljava/lang/Object;)V
        24: return
...
```
Oh I'm an idiot. After specifying the -optimize flag, everything works just fine:

```scala
  public void foo();
    flags: ACC_PUBLIC
    Code:
      stack=3, locals=3, args_size=1
         0: getstatic     #18                 // Field scala/Predef$.MODULE$:Lscala/Predef$;
         3: getstatic     #23                 // Field foo/Optional$.MODULE$:Lfoo/Optional$;
         6: aconst_null
         7: invokevirtual #27                 // Method foo/Optional$.isEmpty$extension:(Ljava/lang/Object;)Z
        10: ifne          17
        13: aconst_null
        14: goto          24
        17: new           #29                 // class foo/C
        20: dup
        21: invokespecial #30                 // Method foo/C."<init>":()V
        24: astore_2
        25: astore_1
        26: getstatic     #35                 // Field scala/Console$.MODULE$:Lscala/Console$;
        29: aload_2
        30: invokevirtual #39                 // Method scala/Console$.println:(Ljava/lang/Object;)V
        33: return
```
Update: this isn't related to value classes, remove `extends AnyVal` for:

```
+ qbin/scalac -optimize -Yinline-warnings sandbox/a.scala
+ qbin/scalac -optimize -Yinline-warnings sandbox/b.scala
sandbox/b.scala:4: warning: Could not inline required method getOrElse because bytecode unavailable.
  def foo = new Optional("").getOrElse("!!!")
                                      ^
sandbox/b.scala:4: warning: At the end of the day, could not inline @inline-marked method getOrElse
  def foo = new Optional("").getOrElse("!!!")
                                      ^
```
I think I  may be hitting this but it is hard to know.  The error I see has no file/line numbers or function names to give a hint at where the failure might be located (see below).  Further, I have determined by very careful steps that under certain circumstances, inlining can fail when a full compile is performed but succeed when a large block of code is added to a function and compile then just touches that compilation unit.

This non-stationary behavior makes bisecting infeasible and I burned a **lot** of time until I realized that the compiler wasn't invariant.  Coupled with the inability to point to a file/line number, it is impractical to isolate a bit of code to demonstrate the problem.  I notice the OP's error message likewise has no file/line info but the names are suggestive.  Can we improve the error message at least?

Suggestions?

From sbt:
```scala
> clean
[success] Total time: 0 s, completed Nov 25, 2014 5:41:56 AM
> compile
[info] Updating {file:/Users/jim/dev/tesla/}hawking...
[info] Updating {file:/Users/jim/dev/tesla/}rosen...
[info] Resolving org.fusesource.jansi#jansi;1.4 ...
[info] Done updating.
[info] Resolving org.fusesource.jansi#jansi;1.4 ...
[info] Done updating.
[info] Updating {file:/Users/jim/dev/tesla/}main...
[info] Resolving org.fusesource.jansi#jansi;1.4 ...
[info] Done updating.
[warn] At the end of the day, could not inline @inline-marked method ->$extension
[warn] one warning found
[success] Total time: 19 s, completed Nov 25, 2014 5:42:19 AM
> 
> sbtVersion
[info] rosen/*:sbtVersion
[info]  0.13.1
[info] hawking/*:sbtVersion
[info]  0.13.1
[info] main/*:sbtVersion
[info]  0.13.1
> scalaVersion
[info] rosen/*:scalaVersion
[info]  2.10.4
[info] hawking/*:scalaVersion
[info]  2.10.4
[info] main/*:scalaVersion
[info]  2.10.4
> 
```
Thanks for the "export compile" trick.  It gave the attached file output which I don't expect to be very useful.  Bisecting with it is a bit like whack-a-mole with deleting the code just makes the problem move to another area.  The file listed in the compiler had no "->" operators in it.

Your conjecture that #6723 may be the root cause is plausible since exceeding inline counts could explain why a "global compile" fails when an "incremental compile" succeeds.

FYI, I tried using sbt 13.6 but that didn't put any line numbers into the warning output, not surprisingly.
