Should get an error here.

```scala
scala> lucmac:scala-lang luc$ scala
Welcome to Scala version 2.11.1 (Java HotSpot(TM) 64-Bit Server VM, Java 1.6.0_65).
Type in expressions to have them evaluated.
Type :help for more information.

scala> class C {
     |   final val K: Int = 20
     |   def f = (1: @annotation.switch) match {
     |     case K => 0
     |     case 2 => 1
     |   }
     | }
defined class C

scala> :javap C
Compiled from "<console>"
public class C extends java.lang.Object

public int f();
  Code:
   Stack=3, Locals=3, Args_size=1
   0:	iconst_1
   1:	istore_1
   2:	aload_0
   3:	invokevirtual	#15; //Method K:()I
   6:	iload_1
   7:	if_icmpne	15
   10:	iconst_0
   11:	istore_2
   12:	goto	22
   15:	iconst_2
   16:	iload_1
   17:	if_icmpne	24
   20:	iconst_1
   21:	istore_2
   22:	iload_2
   23:	ireturn
   24:	new	#17; //class scala/MatchError
   27:	dup
   28:	iload_1
   29:	invokestatic	#23; //Method scala/runtime/BoxesRunTime.boxToInteger:(I)Ljava/lang/Integer;
   32:	invokespecial	#27; //Method scala/MatchError."<init>":(Ljava/lang/Object;)V
   35:	athrow
  LocalVariableTable: 
   Start  Length  Slot  Name   Signature
   0      36      0    this       LC;
```
Noting it's one of the noise-contributing unhandled warnings in the scala build itself.
```scala
[quick.compiler] /mirror/r/scala/src/compiler/scala/tools/nsc/backend/jvm/BCodeBodyBuilder.scala:616: warning: matches with two cases or fewer are emitted using if-then-else instead of switch
[quick.compiler]               (argsSize : @switch) match {
[quick.compiler]                            ^
```
+1

We probably want to have a little excerpt on `@switch` explaining the details of bytecode encoding for the minority that cares about it.
