The problem is that in this context the ??? does not throw the NotImplementedError. It tries of the ??? to the array and it is the jvm that catches the error when it sees that it received something that is not a java primitive value (int in this case). 

The problem seams to be the same with every primitive data types.
Hm, that's not very nice indeed...

```scala
scala> val a = Array(1,2,3)
a: Array[Int] = Array(1, 2, 3)

scala> a(2) = ???
java.lang.VerifyError: Bad type on operand stack
Exception Details:
  Location:
    .<init>()V @22: iastore
  Reason:
    Type 'scala/runtime/Nothing$' (current frame, stack[3]) is not assignable to integer
  Current Frame:
    bci: @22
    flags: { }
    locals: { '' }
    stack: { '', '[I', integer, 'scala/runtime/Nothing$' }
  Bytecode:
    0x0000000: 2ab7 0010 2ab3 0012 2ab2 0017 b600 1b05
    0x0000010: b200 20b6 0024 4fb2 0029 b500 2bb1
```

The final `iastore` cannot possibly succeed in there:

```scala
    Code:
       0: iconst_3
       1: newarray       int
       3: dup
       4: iconst_0
       5: iconst_1
       6: iastore
       7: dup
       8: iconst_1
       9: iconst_2
      10: iastore
      11: dup
      12: iconst_2
      13: iconst_3
      14: iastore
      15: astore_1
      16: aload_1
      17: iconst_2
      18: getstatic     #16                 // Field scala/Predef$.MODULE$:Lscala/Predef$;
      21: invokevirtual #20                 // Method scala/Predef$.$qmark$qmark$qmark:()Lscala/runtime/Nothing$;
      24: iastore
      25: return
```
