```scala
class A {
  final val A = 42
  final val B = 42L
  def test1 = A << 5
  def test2 = (A : Long) << 5
  def test3 = A.toLong << 5
  def test4 = B << 5
  def test5 = scala.reflect.internal.Flags.lateDEFERRED
}
```

```
% qscalac sandbox/test.scala && javap -c -classpath . A | cat -b
     1	Compiled from "test.scala"
     2	public class A {
     3	  public final int A();
     4	    Code:
     5	       0: bipush        42
     6	       2: ireturn

     7	  public final long B();
     8	    Code:
     9	       0: ldc2_w        #16                 // long 42l
    10	       3: lreturn

    11	  public int test1();
    12	    Code:
    13	       0: sipush        1344
    14	       3: ireturn

    15	  public long test2();
    16	    Code:
    17	       0: ldc2_w        #16                 // long 42l
    18	       3: iconst_5
    19	       4: lshl
    20	       5: lreturn

    21	  public long test3();
    22	    Code:
    23	       0: bipush        42
    24	       2: i2l
    25	       3: iconst_5
    26	       4: lshl
    27	       5: lreturn

    28	  public long test4();
    29	    Code:
    30	       0: ldc2_w        #22                 // long 1344l
    31	       3: lreturn

    32	  public long test5();
    33	    Code:
    34	       0: getstatic     #30                 // Field scala/reflect/internal/Flags$.MODULE$:Lscala/reflect/internal/Flags$;
    35	       3: invokevirtual #33                 // Method scala/reflect/internal/Flags$.lateDEFERRED:()J
    36	       6: lreturn

    37	  public A();
    38	    Code:
    39	       0: aload_0
    40	       1: invokespecial #37                 // Method java/lang/Object."<init>":()V
    41	       4: return
    42	}
```
