When compiling a statement which concatenates primitives:

{code:scala|borderStyle=solid}
class Foo {
  def bar(text: String, ch: Char) = text + ch + 1
}
{code}

The following boxing occurs:

{code}
.method public bar : (Ljava/lang/String;C)Ljava/lang/String;
	; method code size: 29 bytes
	.limit stack 2
	.limit locals 3
	new scala/collection/mutable/StringBuilder
	dup
	invokespecial scala/collection/mutable/StringBuilder <init> ()V
	aload_1
	invokevirtual scala/collection/mutable/StringBuilder append [_18]
	iload_2
	invokestatic scala/runtime/BoxesRunTime boxToCharacter (C)Ljava/lang/Character;
	invokevirtual scala/collection/mutable/StringBuilder append [_18]
	iconst_1
	invokestatic scala/runtime/BoxesRunTime boxToInteger (I)Ljava/lang/Integer;
	invokevirtual scala/collection/mutable/StringBuilder append [_18]
	invokevirtual scala/collection/mutable/StringBuilder toString ()Ljava/lang/String;
	areturn
.end method 
.const [_18] = Utf8 (Ljava/lang/Object;)Lscala/collection/mutable/StringBuilder;
{code}

This boxing invokes the generic {{StringBuilder.append(Any)}} method and also produces unnecessary GC overhead.

A proposal would be to optimize the use case of primitive concatenation by invoking the {{StringBuilder.append(primitive)}} methods directly.

{code}
.method public bar : (Ljava/lang/String;C)Ljava/lang/String;
	; method code size: 23 bytes
	.limit stack 2
	.limit locals 3
	new scala/collection/mutable/StringBuilder
	dup
	invokespecial scala/collection/mutable/StringBuilder <init> ()V
	aload_1
	invokevirtual scala/collection/mutable/StringBuilder append [_18]
	iload_2
	invokevirtual scala/collection/mutable/StringBuilder append (C)Lscala/collection/mutable/StringBuilder;
	iconst_1
	invokevirtual scala/collection/mutable/StringBuilder append (I)Lscala/collection/mutable/StringBuilder;
	invokevirtual scala/collection/mutable/StringBuilder toString ()Ljava/lang/String;
	areturn
.end method
{code}

I've submitted a proof-of-concept patch that needs to be polished, but demonstrates optimization of the use case:
https://github.com/melezov/scala/tree/SI-9571

The {{StringBuilderAppendable}} extractor will probably need a better place than in the {{BCodeBodyBuilder.scala}}, and I'm willing to work out a proper test harness, if this makes sense.
[~limo] thanks a lot for your patch! I refined it a bit and submitted it in https://github.com/scala/scala/pull/4944
