I found that scalac infers that synchronized entire an entire method's code means that the method should be synchronized.  On Function0#apply, this means that it synchronizes the apply method.  However, it doesn't synchronize Function0#apply$mcV$sp, presumably thinking that folks will not call that method directly.  However, scalac compiles function invocations down to call that method directly.

This means that methods which are marked synchronized are not really synchronized.

```scala
class Bar(foo: () => Unit) {
  def apply(): Unit = foo()
}

class Foo extends (() => Unit) {
  def apply(): Unit = synchronized {
    println("i'm synchronized!")
  }
}
```

javap -c Foo (edited for clarity)

```scala
...
  public synchronized void apply();
    Code:
       0: aload_0
       1: invokevirtual #64                 // Method apply$mcV$sp:()V
       4: return

  public void apply$mcV$sp();
    Code:
       0: getstatic     #70                 // Field scala/Predef$.MODULE$:Lscala/Predef$;
       3: ldc           #72                 // String i'm synchronized!
       5: invokevirtual #76                 // Method scala/Predef$.println:(Ljava/lang/Object;)V
       8: return
```

javap -c Bar (edited for clarity)

```scala
  public void apply();
    Code:
       0: aload_0
       1: getfield      #15                 // Field foo:Lscala/Function0;
       4: invokeinterface #20,  1           // InterfaceMethod scala/Function0.apply$mcV$sp:()V
       9: return
```
Ouch! Thanks for the report.

A workaround is to restructure as:

```scala
  def apply(): Unit = {
    val self = this
    self.synchronized {
      println("i'm synchronized!")
    }
  }
```

The compiler looks for method bodies of the shape `def foo(...) = this.synchronized { ... }` and marks with a flag that will result ACC_SYNCHRONIZED in the bytecode. Other usages of `synchronized` (e.g. in my workaround) result in explicit bytecode for monitorenter / monitorexit.

https://github.com/scala/scala/blob/79e7334f93da4717ee846f74e48ab53533e6756d/src/compiler/scala/tools/nsc/transform/UnCurry.scala#L357-L371

Fixing this will involve something like:

```
diff --git a/src/compiler/scala/tools/nsc/transform/SpecializeTypes.scala b/src/compiler/scala/tools/nsc/transform/SpecializeTypes.scala
index 40ab8c0..dd47e62 100644
--- a/src/compiler/scala/tools/nsc/transform/SpecializeTypes.scala
+++ b/src/compiler/scala/tools/nsc/transform/SpecializeTypes.scala
@@ -1662,6 +1662,7 @@ abstract class SpecializeTypes extends InfoTransform with TypingTransformers {
               val tree1 = addBody(ddef, target)
               (new ChangeOwnerTraverser(target, tree1.symbol))(tree1.rhs)
               debuglog("changed owners, now: " + tree1)
+              if (target.hasFlag(Flags.SYNCHRONIZED)) ddef.symbol.setFlag(Flags.SYNCHRONIZED)
               deriveDefDef(tree1)(transform)

             case SpecialOverload(original, env) =>
```

I'll flesh this out and submit a patch for 2.11.9 + 2.12.x in the next week.
