{code}
val a = Array("a", "b")
{code}

should be equivalent to

{code}
a = {
    val x = new Array[String](2)
    x(0) = "a"
    x(1) = "b"
    x
}
{code}

However, first fragment is compiled to

{code}
   5:	getstatic	SI-18; //Field scala/runtime/ScalaRunTime$$.MODULE$$:Lscala/runtime/ScalaRunTime$$;
   8:	getstatic	SI-23; //Field scala/Array$$.MODULE$$:Lscala/Array$$;
   11:	new	SI-25; //class scala/runtime/BoxedObjectArray
   14:	dup
   15:	iconst_2
   16:	anewarray	SI-27; //class java/lang/String
   19:	dup
   20:	iconst_0
   21:	ldc	SI-28; //String a
   23:	aastore
   24:	dup
   25:	iconst_1
   26:	ldc	SI-30; //String b
   28:	aastore
   29:	checkcast	SI-32; //class "[Ljava/lang/Object;"
   32:	invokespecial	SI-35; //Method scala/runtime/BoxedObjectArray."<init>":([Ljava/lang/Object;)V
   35:	invokevirtual	SI-39; //Method scala/Array$$.apply:(Lscala/Seq;)Lscala/runtime/BoxedArray;
   38:	ldc	SI-27; //class java/lang/String
   40:	invokevirtual	SI-43; //Method scala/runtime/ScalaRunTime$$.arrayValue:(Lscala/runtime/BoxedArray;Ljava/lang/Class;)Ljava/lang/Object;
   43:	astore_1
   44:	aload_1
   45:	instanceof	SI-45; //class scala/runtime/BoxedArray
   48:	ifeq	66
   51:	getstatic	SI-18; //Field scala/runtime/ScalaRunTime$$.MODULE$$:Lscala/runtime/ScalaRunTime$$;
   54:	aload_1
   55:	checkcast	SI-45; //class scala/runtime/BoxedArray
   58:	ldc	SI-27; //class java/lang/String
   60:	invokevirtual	SI-43; //Method scala/runtime/ScalaRunTime$$.arrayValue:(Lscala/runtime/BoxedArray;Ljava/lang/Class;)Ljava/lang/Object;
   63:	goto	67
   66:	aload_1
   67:	checkcast	SI-46; //class "[Ljava/lang/String;"
   70:	putfield	SI-50; //Field a:[Ljava/lang/String;
{code}

There are unnecessary boxing to !BoxedObjectArray, invocation of Array.apply and !ScalaRunTime.arrayValue.

Compare with second:

{code}
   5:	iconst_2
   6:	anewarray	SI-14; //class java/lang/String
   9:	astore_1
   10:	aload_1
   11:	iconst_0
   12:	ldc	SI-15; //String a
   14:	aastore
   15:	aload_1
   16:	iconst_1
   17:	ldc	SI-17; //String b
   19:	aastore
   20:	aload_1
   21:	putfield	SI-21; //Field a:[Ljava/lang/String;
{code}
For the record, this is much improved in the trunk (2.8.0 beta at the time of checking):

{code}
   5:   getstatic       SI-23; //Field scala/Array$$.MODULE$$:Lscala/Array$$;
   8:   getstatic       SI-28; //Field scala/Predef$$.MODULE$$:Lscala/Predef$$;
   11:  iconst_2
   12:  anewarray       SI-30; //class java/lang/String
   15:  dup
   16:  iconst_0
   17:  ldc     SI-31; //String a
   19:  aastore
   20:  dup
   21:  iconst_1
   22:  ldc     SI-33; //String b
   24:  aastore
   25:  checkcast       SI-35; //class "[Ljava/lang/Object;"
   28:  invokevirtual   SI-39; //Method scala/Predef$$.wrapRefArray:([Ljava/lang/Object;)Lscala/collection/mutable/WrappedArray;
   31:  getstatic       SI-44; //Field scala/reflect/ClassManifest$$.MODULE$$:Lscala/reflect/ClassManifest$$;
   34:  ldc     SI-30; //class java/lang/String
   36:  invokevirtual   SI-48; //Method scala/reflect/ClassManifest$$.classType:(Ljava/lang/Class;)Lscala/reflect/ClassManifest;
   39:  invokevirtual   SI-52; //Method scala/Array$$.apply:(Lscala/collection/Seq;Lscala/reflect/ClassManifest;)Ljava/lang/Object;
   42:  checkcast       SI-53; //class "[Ljava/lang/String;"
   45:  putfield        SI-11; //Field a:[Ljava/lang/String;
{code}

Is it worth keeping this ticket open?
