Why is the following function not tail-call optimized?  I see two recursive calls in the byte code.  Here's the function:
```scala
class Test {
  var args: Array[String] = _
  def searchFrom(i: Int): Int =
    if (i >= args.length)  -1
    else if (args(i).startsWith("-"))  searchFrom(i + 1) 
    else if (args(i).endsWith(".scala"))  i
    else searchFrom(i + 1)
}
```
Here's the output:
```scala
public int searchFrom(int);
  Code:
   0:   iload_1
   1:   aload_0
   2:   invokevirtual   SI-19; //Method args:()[Ljava/lang/String;
   5:   arraylength
   6:   if_icmplt       13
   9:   iconst_m1
   10:  goto    62
   13:  aload_0
   14:  invokevirtual   SI-19; //Method args:()[Ljava/lang/String;
   17:  iload_1
   18:  aaload
   19:  ldc     SI-21; //String -
   21:  invokevirtual   SI-27; //Method java/lang/String.startsWith:(Ljava/lang/String;)Z
   24:  ifeq    37
   27:  aload_0
   28:  iload_1
   29:  iconst_1
   30:  iadd
   31:  invokevirtual   SI-29; //Method searchFrom:(I)I
   34:  goto    62
   37:  aload_0
   38:  invokevirtual   SI-19; //Method args:()[Ljava/lang/String;
   41:  iload_1
   42:  aaload
   43:  ldc     SI-31; //String .scala
   45:  invokevirtual   SI-34; //Method java/lang/String.endsWith:(Ljava/lang/String;)Z
   48:  ifeq    55
   51:  iload_1
   52:  goto    62
   55:  aload_0
   56:  iload_1
   57:  iconst_1
   58:  iadd
   59:  invokevirtual   SI-29; //Method searchFrom:(I)I
   62:  ireturn
```

Because the method is not final. See #709 :)
